easys7comm/__init__.py
easys7comm/plc.py
easys7comm/plc_connection.py
easys7comm/plc_parse_address.py
easys7comm/plc_reader.py
easys7comm/plc_types.py
easys7comm/plc_writer.py
easys7comm/__pycache__/__init__.cpython-313.pyc
easys7comm/__pycache__/plc.cpython-313.pyc
easys7comm/__pycache__/plc_connection.cpython-313.pyc
easys7comm/__pycache__/plc_reader.cpython-313.pyc
easys7comm/__pycache__/plc_types.cpython-313.pyc
easys7comm/__pycache__/plc_writer.cpython-313.pyc
easys7comm/utils/__pycache__/plc_parse_address.cpython-313.pyc
easys7comm-0.2.4.dist-info/LICENSE
easys7comm-0.2.4.dist-info/METADATA
easys7comm-0.2.4.dist-info/WHEEL
easys7comm-0.2.4.dist-info/top_level.txt
easys7comm-0.2.4.dist-info/RECORD
