Metadata-Version: 2.2
Name: easys7comm
Version: 0.2.4
Summary: A abstraction of python-snap7
Author-email: Allan Marum <allan.marum@gmail.com>
Project-URL: Homepage, https://github.com/allanmarum/EasyS7Comm
Project-URL: Issues, https://github.com/allanmarum/EasyS7Comm/issues
Classifier: Programming Language :: Python :: 3
Classifier: Operating System :: Microsoft :: Windows
Classifier: License :: OSI Approved :: MIT License
Requires-Python: >=3.13
License-File: LICENSE
